MANIFEST.in
README.md
setup.cfg
setup.py
myui/__init__.py
myui/__init__.pyc
myui.egg-info/PKG-INFO
myui.egg-info/SOURCES.txt
myui.egg-info/dependency_links.txt
myui.egg-info/entry_points.txt
myui.egg-info/requires.txt
myui.egg-info/top_level.txt
myui/controllers/example.py
myui/controllers/home.py
myui/templates/base.html
myui/templates/example.html
myui/templates/template.j2
myui/templates/template2.j2