Metadata-Version: 1.0
Name: myui
Version: 0.2.1
Summary: MyUI - Easily customizable Tornado UI
Home-page: https://github.com/teriyakichild/myui
Author: Tony Rogers
Author-email: tony.rogers@rackspace.com
License: internal use
Platform: UNKNOWN
